comfyui_workflow_templates_media_video/__init__.py
comfyui_workflow_templates_media_video/templates/03_video_wan2_2_14B_i2v_subgraphed-1.webp
comfyui_workflow_templates_media_video/templates/03_video_wan2_2_14B_i2v_subgraphed.json
comfyui_workflow_templates_media_video/templates/hunyuan_video_text_to_video-1.webp
comfyui_workflow_templates_media_video/templates/hunyuan_video_text_to_video.json
comfyui_workflow_templates_media_video/templates/image_to_video_wan-1.webp
comfyui_workflow_templates_media_video/templates/image_to_video_wan.json
comfyui_workflow_templates_media_video/templates/ltxv_image_to_video-1.webp
comfyui_workflow_templates_media_video/templates/ltxv_image_to_video.json
comfyui_workflow_templates_media_video/templates/ltxv_text_to_video-1.webp
comfyui_workflow_templates_media_video/templates/ltxv_text_to_video.json
comfyui_workflow_templates_media_video/templates/template-Animation_Trajectory_Control_Wan_ATI-1.webp
comfyui_workflow_templates_media_video/templates/template-Animation_Trajectory_Control_Wan_ATI.json
comfyui_workflow_templates_media_video/templates/templates-3D_logo_texture_animation-1.webp
comfyui_workflow_templates_media_video/templates/templates-3D_logo_texture_animation.json
comfyui_workflow_templates_media_video/templates/text_to_video_wan-1.webp
comfyui_workflow_templates_media_video/templates/text_to_video_wan.json
comfyui_workflow_templates_media_video/templates/txt_to_image_to_video-1.webp
comfyui_workflow_templates_media_video/templates/txt_to_image_to_video.json
comfyui_workflow_templates_media_video/templates/utility-normal_crafter-video-1.webp
comfyui_workflow_templates_media_video/templates/utility-normal_crafter-video-2.webp
comfyui_workflow_templates_media_video/templates/utility-normal_crafter-video.json
comfyui_workflow_templates_media_video/templates/video_humo-1.webp
comfyui_workflow_templates_media_video/templates/video_humo.json
comfyui_workflow_templates_media_video-0.3.38.dist-info/METADATA
comfyui_workflow_templates_media_video-0.3.38.dist-info/WHEEL
comfyui_workflow_templates_media_video-0.3.38.dist-info/top_level.txt
comfyui_workflow_templates_media_video-0.3.38.dist-info/RECORD
