Metadata-Version: 2.4
Name: comfyui-workflow-templates-media-video
Version: 0.3.38
Summary: Media bundle containing video workflow assets
License-Expression: MIT
Requires-Python: >=3.9
